AUTHORS
MANIFEST.in
README.md
requirements-min-django.txt
requirements-test.txt
requirements.txt
setup.py
bin/chroniker
chroniker/__init__.py
chroniker/admin.py
chroniker/apps.py
chroniker/constants.py
chroniker/models.py
chroniker/settings.py
chroniker/utils.py
chroniker/views.py
chroniker/widgets.py
chroniker/management/__init__.py
chroniker/management/commands/__init__.py
chroniker/management/commands/calculate_job_chain.py
chroniker/management/commands/check_monitor.py
chroniker/management/commands/cron.py
chroniker/management/commands/cron_clean.py
chroniker/management/commands/cronserver.py
chroniker/management/commands/run_job.py
chroniker/management/commands/test_status_update.py
chroniker/migrations/0001_initial.py
chroniker/migrations/0002_auto_20190415_0925.py
chroniker/migrations/0003_auto_20200822_2026.py
chroniker/migrations/0004_auto_20240328_2035.py
chroniker/migrations/__init__.py
chroniker/static/chroniker/js/dygraph-combined.js
chroniker/templates/admin/chroniker/job/change_form.html
chroniker/templates/admin/chroniker/job/change_list.html
chroniker/templates/admin/chroniker/job/duration_graph.html
chroniker/templates/chroniker/error_message.txt
chroniker/templatetags/__init__.py
chroniker/templatetags/chroniker_tags.py
chroniker/tests/__init__.py
chroniker/tests/commands.py
chroniker/tests/manage.py
chroniker/tests/models.py
chroniker/tests/settings.py
chroniker/tests/tests.py
chroniker/tests/urls.py
chroniker/tests/views.py
chroniker/tests/fixtures/jobs_by_command.json
chroniker/tests/fixtures/jobs_by_command_args.json
chroniker/tests/fixtures/jobs_by_name.json
chroniker/tests/fixtures/test_jobs.json
chroniker/tests/management/__init__.py
chroniker/tests/management/commands/__init__.py
chroniker/tests/management/commands/test_cron_clean.py
chroniker/tests/management/commands/test_error.py
chroniker/tests/management/commands/test_sleeper.py
chroniker/tests/management/commands/test_success.py
chroniker/tests/management/commands/test_waiter.py
django_chroniker.egg-info/PKG-INFO
django_chroniker.egg-info/SOURCES.txt
django_chroniker.egg-info/dependency_links.txt
django_chroniker.egg-info/not-zip-safe
django_chroniker.egg-info/requires.txt
django_chroniker.egg-info/top_level.txt
