Metadata-Version: 2.1
Name: django-chroniker
Version: 1.0.24
Summary: Easily control cron jobs via Django's admin.
Home-page: https://github.com/chrisspen/django-chroniker
Author: Chris Spencer
Author-email: chrisspen@gmail.com
License: BSD
Platform: UNKNOWN
Classifier: Development Status :: 6 - Mature
Classifier: Environment :: Web Environment
Classifier: Intended Audience :: Developers
Classifier: License :: OSI Approved :: BSD License
Classifier: Operating System :: OS Independent
Classifier: Programming Language :: Python
Classifier: Programming Language :: Python :: 3.8
Classifier: Framework :: Django
